pyicloud/__init__.py
pyicloud/base.py
pyicloud/cmdline.py
pyicloud/const.py
pyicloud/cookie_jar.py
pyicloud/exceptions.py
pyicloud/session.py
pyicloud/srp_password.py
pyicloud/ssl_context.py
pyicloud/utils.py
pyicloud/.vscode/launch.json
pyicloud/services/__init__.py
pyicloud/services/account.py
pyicloud/services/base.py
pyicloud/services/calendar.py
pyicloud/services/contacts.py
pyicloud/services/drive.py
pyicloud/services/findmyiphone.py
pyicloud/services/hidemyemail.py
pyicloud/services/photos.py
pyicloud/services/reminders.py
pyicloud/services/ubiquity.py
pyicloud-2.2.0.dist-info/licenses/LICENSE.txt
pyicloud-2.2.0.dist-info/METADATA
pyicloud-2.2.0.dist-info/WHEEL
pyicloud-2.2.0.dist-info/entry_points.txt
pyicloud-2.2.0.dist-info/top_level.txt
pyicloud-2.2.0.dist-info/RECORD
