Metadata-Version: 2.4
Name: pyicloud
Version: 2.2.0
Summary: PyiCloud is a module which allows pythonistas to interact with iCloud webservices.
Author: The PyiCloud Authors
License-Expression: MIT
Project-URL: homepage, https://github.com/timlaing/pyicloud
Project-URL: download, https://github.com/timlaing/pyicloud/releases/latest
Project-URL: bug_tracker, https://github.com/timlaing/pyicloud/issues
Project-URL: repository, https://github.com/timlaing/pyicloud
Keywords: icloud,find-my-iphone
Classifier: Development Status :: 5 - Production/Stable
Classifier: Intended Audience :: Developers
Classifier: Operating System :: OS Independent
Classifier: Programming Language :: Python
Classifier: Programming Language :: Python :: 3 :: Only
Classifier: Programming Language :: Python :: 3
Classifier: Programming Language :: Python :: 3.10
Classifier: Programming Language :: Python :: 3.11
Classifier: Programming Language :: Python :: 3.12
Classifier: Programming Language :: Python :: 3.13
Classifier: Topic :: Software Development :: Libraries
Requires-Python: >=3.10
License-File: LICENSE.txt
Requires-Dist: certifi>=2024.12.14
Requires-Dist: click>=8.1.8
Requires-Dist: fido2>=2.0.0
Requires-Dist: keyring>=25.6.0
Requires-Dist: keyrings.alt>=5.0.2
Requires-Dist: requests>=2.31.0
Requires-Dist: srp>=1.0.21
Requires-Dist: tzlocal==5.3.1
Provides-Extra: test
Requires-Dist: isort>=5.11.5; extra == "test"
Requires-Dist: pre-commit>=2.21.0; extra == "test"
Requires-Dist: pylint>=3.3.4; extra == "test"
Requires-Dist: pylint-strict-informational>=0.1; extra == "test"
Requires-Dist: pytest>=8.3.5; extra == "test"
Requires-Dist: pytest-cov>=4.1.0; extra == "test"
Requires-Dist: pytest-socket>=0.6.0; extra == "test"
Requires-Dist: ruff>=0.9.9; extra == "test"
Dynamic: license-file
